gen_gherkin/__init__.py
gen_gherkin/behavior.feature.jinja2
gen_gherkin/behavior_generator.aac
gen_gherkin/gen_gherkin_helpers.py
gen_gherkin/generate_gherkin_feature_files.aac
gen_gherkin/generate_gherkin_feature_files_impl.py
aac_gen_gherkin-0.1.3.dist-info/METADATA
aac_gen_gherkin-0.1.3.dist-info/WHEEL
aac_gen_gherkin-0.1.3.dist-info/entry_points.txt
aac_gen_gherkin-0.1.3.dist-info/top_level.txt
aac_gen_gherkin-0.1.3.dist-info/RECORD
